appqos/__init__.py
appqos/__main__.py
appqos/__version__.py
appqos/appqos.py
appqos/cache_ops.py
appqos/caps.py
appqos/common.py
appqos/config.py
appqos/config_store.py
appqos/log.py
appqos/manager.py
appqos/pid_ops.py
appqos/power.py
appqos/power_common.py
appqos/pqos_api.py
appqos/sstbf.py
appqos/stats.py
appqos/rest/rest_app.py
appqos/rest/rest_caps_cpu.py
appqos/rest/rest_exceptions.py
appqos/rest/rest_misc.py
appqos/rest/rest_pool.py
appqos/rest/rest_power.py
appqos/rest/rest_rdt.py
appqos/rest/rest_server.py
appqos/schema/add_app.json
appqos/schema/add_app_response.json
appqos/schema/add_pool.json
appqos/schema/add_pool_response.json
appqos/schema/add_power.json
appqos/schema/add_power_response.json
appqos/schema/appqos.json
appqos/schema/definitions.json
appqos/schema/get_app_all_response.json
appqos/schema/get_app_response.json
appqos/schema/get_caps_cpu_response.json
appqos/schema/get_caps_l2ca_response.json
appqos/schema/get_caps_l3ca_response.json
appqos/schema/get_caps_mba_ctrl_response.json
appqos/schema/get_caps_mba_response.json
appqos/schema/get_caps_rdt_iface_response.json
appqos/schema/get_caps_response.json
appqos/schema/get_pool_all_response.json
appqos/schema/get_pool_response.json
appqos/schema/get_power_all_response.json
appqos/schema/get_power_response.json
appqos/schema/get_sstbf_response.json
appqos/schema/get_stats_response.json
appqos/schema/modify_app.json
appqos/schema/modify_cdp.json
appqos/schema/modify_mba_ctrl.json
appqos/schema/modify_pool.json
appqos/schema/modify_power.json
appqos/schema/modify_rdt_iface.json
appqos/schema/modify_sstbf.json
appqos/schema/pool.json
appqos-4.6.0.dist-info/LICENSE
appqos-4.6.0.dist-info/METADATA
appqos-4.6.0.dist-info/WHEEL
appqos-4.6.0.dist-info/top_level.txt
appqos-4.6.0.dist-info/RECORD
