Metadata-Version: 2.1
Name: appqos
Version: 4.6.0
Summary: App QoS is a software created to demonstrate the use of Intel(R) RDT technologies (CAT, MBA) to improve QoS for applications via partitioning system resources.
Home-page: https://github.com/intel/intel-cmt-cat
Author-email: Michal Aleksinski <michalx.aleksinski@intel.com>, Wojciech Andralojc <wojciechx.andralojc@intel.com>, Adrian Boczkowski <adrianx.boczkowski@intel.com>, Khawar Abbasi <khawar.abbasi@intel.com>
Maintainer-email: Michal Aleksinski <michalx.aleksinski@intel.com>
License: BSD LICENSE
Project-URL: Homepage, https://github.com/intel/intel-cmt-cat
Project-URL: Source Code, https://github.com/intel/intel-cmt-cat
Project-URL: Bug Tracker, https://github.com/intel/intel-cmt-cat/issues
Classifier: Programming Language :: Python :: 3
Classifier: Programming Language :: Python :: 3 :: Only
Classifier: Programming Language :: Python :: 3.6
Classifier: License :: OSI Approved :: BSD License
Requires-Python: >=3.6
License-File: LICENSE
Requires-Dist: pqos (==4.6.0)
Requires-Dist: jsonschema
Requires-Dist: pexpect
Requires-Dist: flask
Requires-Dist: flask-restful
Requires-Dist: gevent
Requires-Dist: psutil
Provides-Extra: cors
Requires-Dist: flask-cors ; extra == 'cors'
Provides-Extra: dev
Requires-Dist: bandit ; extra == 'dev'
Requires-Dist: pylint ; extra == 'dev'
Requires-Dist: pytest ; extra == 'dev'
Requires-Dist: pytest-cov ; extra == 'dev'
Requires-Dist: mock ; extra == 'dev'
Requires-Dist: caniusepython3 ; extra == 'dev'
Requires-Dist: requests ; extra == 'dev'
Requires-Dist: codespell ; extra == 'dev'
